[{"status":"read","comment":"Steven Wolfram给Mathematica、NKS有个人或精神关系的前人写的学术传记和个人唁文，或者说着迷于\"简单规则，复杂现象\"的松散的一群人的精神族谱。每篇都像是NKS的软文，但这是他一辈子的主线，是诚恳的。","updated":"2016-07-22 08:12:35","user_id":"1000001","book_id":"26832406","id":1064740682,"rating":5,"book_title":"Idea Makers","url":"https://book.douban.com/subject/26832406/"},{"status":"read","comment":"喜欢硬科幻的，推荐这本。期待电影或剧。","updated":"2016-06-10 10:04:23","user_id":"1000001","book_id":"26335214","id":1050306937,"rating":5,"book_title":"Seveneves","url":"https://book.douban.com/subject/26335214/"},{"status":"read","comment":"谢谢Kim推荐","updated":"2016-02-21 17:58:56","user_id":"1000001","book_id":"6897158","id":1013816442,"rating":4,"book_title":"Connectome","url":"https://book.douban.com/subject/6897158/"},{"status":"read","comment":"娱乐性挺强的","updated":"2016-02-21 17:57:32","user_id":"1000001","book_id":"26416854","id":1013815947,"rating":4,"book_title":"Primates of Park Avenue","url":"https://book.douban.com/subject/26416854/"},{"status":"read","comment":"名言录而已","updated":"2016-02-21 17:56:06","user_id":"1000001","book_id":"5363860","id":1013815488,"rating":3,"book_title":"The Bed of Procrustes","url":"https://book.douban.com/subject/5363860/"},{"status":"read","updated":"2016-02-21 17:54:33","user_id":"1000001","book_id":"3424266","id":1013814970,"rating":4,"book_title":"Flow","url":"https://book.douban.com/subject/3424266/"},{"status":"read","comment":"给zappos(可能是错误的)启发的书。","updated":"2016-02-21 17:53:45","user_id":"1000001","book_id":"26341994","id":1013814713,"rating":4,"book_title":"Reinventing Organizations","url":"https://book.douban.com/subject/26341994/"},{"status":"read","comment":"可以更了解内向的人，自己或别人。","updated":"2016-02-21 17:51:33","user_id":"1000001","tags":["心理学"],"book_id":"6896459","id":960830025,"rating":4,"book_title":"Quiet","url":"https://book.douban.com/subject/6896459/"},{"status":"read","updated":"2016-02-21 17:49:47","user_id":"1000001","book_id":"26586799","id":1013813399,"rating":4,"book_title":"创业无畏","url":"https://book.douban.com/subject/26586799/"},{"status":"read","updated":"2016-02-21 17:47:30","user_id":"1000001","book_id":"25904521","id":1013812644,"rating":5,"book_title":"Sapiens","url":"https://book.douban.com/subject/25904521/"},{"status":"read","comment":"美国精神的代表, 所以副标题是\"an American Life\". 豆瓣App下看完书的第一个评分. (Via Elon Musk)","updated":"2014-11-12 19:03:53","user_id":"1000001","book_id":"1365773","id":862133022,"rating":4,"book_title":"Benjamin Franklin","url":"https://book.douban.com/subject/1365773/"},{"status":"read","comment":"值得一读，虽然戏剧化得稍过了一点点。","updated":"2014-04-27 14:46:55","user_id":"1000001","tags":["创业","商业","管理"],"book_id":"24661633","id":800867660,"rating":4,"book_title":"Hatching Twitter","url":"https://book.douban.com/subject/24661633/"},{"status":"read","comment":"You'll love it,  or you'll be bored to death. There's no other way.","updated":"2013-01-27 13:15:08","user_id":"1000001","tags":["复杂系统","哲学"],"book_id":"10545758","id":622961423,"rating":5,"book_title":"Antifragile","url":"https://book.douban.com/subject/10545758/"},{"status":"read","comment":"才知道Michael Crichton已经挂了。可惜。这本如果是他单人写完的话，可能悬念会更意外惊喜一点。","updated":"2011-12-22 16:21:36","user_id":"1000001","tags":["科幻"],"book_id":"4445111","id":472429679,"rating":3,"book_title":"Micro","url":"https://book.douban.com/subject/4445111/"},{"status":"read","comment":"大脑在碎片化, 我们变成吞噬拉撒信息的机器。","updated":"2010-07-24 12:57:09","user_id":"1000001","tags":["互联网"],"book_id":"4096693","id":270770325,"rating":4,"book_title":"The Shallows","url":"https://book.douban.com/subject/4096693/"},{"status":"read","comment":"via Jean","updated":"2010-06-29 19:06:16","user_id":"1000001","tags":["金融","经济"],"book_id":"4069561","id":224120245,"rating":4,"book_title":"Too Big to Fail","url":"https://book.douban.com/subject/4069561/"},{"status":"read","comment":"在iBooks上买的第二本书。","updated":"2010-04-27 21:14:37","user_id":"1000001","tags":["科幻"],"book_id":"4773743","id":243174313,"rating":4,"book_title":"WWW: Watch","url":"https://book.douban.com/subject/4773743/"},{"status":"read","comment":"Www is alive","updated":"2010-04-22 13:56:25","user_id":"1000001","tags":["科幻"],"book_id":"4763390","id":243172660,"rating":4,"book_title":"WWW: Wake","url":"https://book.douban.com/subject/4763390/"},{"status":"read","comment":"DNA,  进化论，新人类。","updated":"2010-03-25 10:46:02","user_id":"1000001","tags":["科幻","进化论"],"book_id":"2031372","id":232960668,"rating":4,"book_title":"Darwin's Radio","url":"https://book.douban.com/subject/2031372/"},{"status":"read","updated":"2010-02-09 12:52:21","user_id":"1000001","tags":["概率"],"book_id":"1459548","id":214975979,"rating":4,"book_title":"Bringing Down the House","url":"https://book.douban.com/subject/1459548/"},{"status":"read","updated":"2009-12-01 23:15:14","user_id":"1000001","book_id":"1777630","id":185092241,"rating":5,"book_title":"The Selfish Gene","url":"https://book.douban.com/subject/1777630/"},{"status":"read","updated":"2009-09-21 17:23:17","user_id":"1000001","tags":["设计","城市规划"],"book_id":"1370957","id":161047523,"rating":4,"book_title":"The City Shaped","url":"https://book.douban.com/subject/1370957/"},{"status":"read","updated":"2009-08-25 22:58:27","user_id":"1000001","tags":["杂文"],"book_id":"1370770","id":44211,"rating":4,"book_title":"How to Travel with a Salmon & Other Essays","url":"https://book.douban.com/subject/1370770/"},{"status":"read","updated":"2009-08-25 22:55:23","user_id":"1000001","tags":["设计","人类学"],"book_id":"3841622","id":138528571,"rating":3,"book_title":"YOU ARE HERE","url":"https://book.douban.com/subject/3841622/"},{"status":"read","updated":"2009-07-08 18:27:29","user_id":"1000001","tags":["文化"],"book_id":"1456407","id":137120837,"rating":4,"book_title":"Invisible Cities","url":"https://book.douban.com/subject/1456407/"},{"status":"read","updated":"2009-04-22 23:44:58","user_id":"1000001","tags":["复杂系统","经济"],"book_id":"2072159","id":115106464,"rating":4,"book_title":"The Black Swan","url":"https://book.douban.com/subject/2072159/"},{"status":"read","updated":"2009-02-01 10:56:05","user_id":"1000001","tags":["经济"],"book_id":"1479360","id":92469107,"rating":4,"book_title":"The Undercover Economist","url":"https://book.douban.com/subject/1479360/"},{"status":"read","comment":"和Spin相比差不少","updated":"2008-09-16 11:19:55","user_id":"1000001","tags":["科幻"],"book_id":"3127420","id":59784432,"rating":3,"book_title":"Axis","url":"https://book.douban.com/subject/3127420/"},{"status":"read","comment":"哈哈哈，我是豆瓣上第一个“读过”的吗?  (其实我是想打三星半)","updated":"2008-08-24 14:36:06","user_id":"1000001","tags":["复杂系统","科幻"],"book_id":"2123484","id":56037964,"rating":4,"book_title":"Daemon","url":"https://book.douban.com/subject/2123484/"},{"status":"read","updated":"2008-07-27 17:37:35","user_id":"1000001","tags":["文化","人类学"],"book_id":"2371317","id":27724255,"rating":5,"book_title":"The God Delusion","url":"https://book.douban.com/subject/2371317/"},{"status":"read","comment":"雷声大，雨点小","updated":"2008-07-09 00:41:58","user_id":"1000001","tags":["设计"],"book_id":"1459599","id":48306391,"rating":3,"book_title":"Ambient Findability","url":"https://book.douban.com/subject/1459599/"},{"status":"read","updated":"2008-07-05 01:08:45","user_id":"1000001","tags":["经济"],"book_id":"2775770","id":47783252,"rating":5,"book_title":"Small Is Beautiful","url":"https://book.douban.com/subject/2775770/"},{"status":"read","updated":"2008-07-04 17:39:25","user_id":"1000001","tags":["科幻"],"book_id":"1993294","id":32177324,"rating":5,"book_title":"Spin","url":"https://book.douban.com/subject/1993294/"},{"status":"read","updated":"2008-05-24 14:15:55","user_id":"1000001","tags":["小说"],"book_id":"2079345","id":32893391,"rating":4,"book_title":"侠隐","url":"https://book.douban.com/subject/2079345/"},{"status":"read","comment":"蜻蜓点水","updated":"2008-05-24 14:15:18","user_id":"1000001","tags":["商业","复杂系统"],"book_id":"1918678","id":41519568,"rating":3,"book_title":"The Starfish and the Spider","url":"https://book.douban.com/subject/1918678/"},{"status":"read","updated":"2008-02-05 20:39:50","user_id":"1000001","tags":["人类学","文化"],"book_id":"2351927","id":26260537,"rating":4,"book_title":"Why Beautiful People Have More Daughters","url":"https://book.douban.com/subject/2351927/"},{"status":"read","updated":"2008-01-01 01:26:55","user_id":"1000001","tags":["商业","传记"],"book_id":"1763398","id":26256990,"rating":3,"book_title":"Losing My Virginity","url":"https://book.douban.com/subject/1763398/"},{"status":"read","updated":"2007-12-16 12:35:34","user_id":"1000001","tags":["复杂系统"],"book_id":"1479542","id":26340167,"rating":0,"book_title":"The Wisdom of Crowds","url":"https://book.douban.com/subject/1479542/"},{"status":"read","updated":"2007-11-21 01:06:20","user_id":"1000001","tags":["管理"],"book_id":"1966719","id":11541370,"rating":4,"book_title":"Founders at Work","url":"https://book.douban.com/subject/1966719/"},{"status":"read","comment":"A  brilliant, up-to-date and much needed review of social sciences from a physicist , who knows quite a few things about complex systems and self-organization","updated":"2007-10-14 12:50:26","user_id":"1000001","tags":["复杂系统","传播"],"book_id":"2277047","id":21793551,"rating":5,"book_title":"The Social Atom","url":"https://book.douban.com/subject/2277047/"},{"status":"read","updated":"2007-10-12 06:13:40","user_id":"1000001","tags":["畅销"],"book_id":"1462647","id":21821024,"rating":3,"book_title":"Blink","url":"https://book.douban.com/subject/1462647/"},{"status":"read","updated":"2007-08-13 10:53:27","user_id":"1000001","tags":["杂文"],"book_id":"1003284","id":18566390,"rating":4,"book_title":"退步集","url":"https://book.douban.com/subject/1003284/"},{"status":"read","updated":"2007-07-04 12:16:21","user_id":"1000001","tags":["复杂系统"],"book_id":"1499220","id":16581052,"rating":3,"book_title":"Emergence","url":"https://book.douban.com/subject/1499220/"},{"status":"read","updated":"2007-06-09 11:23:30","user_id":"1000001","tags":["小说"],"book_id":"1291231","id":7104,"rating":4,"book_title":"The Curious Incident of the Dog in the Night-Time","url":"https://book.douban.com/subject/1291231/"},{"status":"read","updated":"2007-05-24 11:38:49","user_id":"1000001","tags":["商业","互联网"],"book_id":"1395491","id":14696922,"rating":4,"book_title":"The Perfect Store","url":"https://book.douban.com/subject/1395491/"},{"status":"read","updated":"2007-03-09 12:20:20","user_id":"1000001","tags":["管理"],"book_id":"1394499","id":11500205,"rating":4,"book_title":"Good to Great","url":"https://book.douban.com/subject/1394499/"},{"status":"read","updated":"2007-03-09 12:19:54","user_id":"1000001","tags":["金融"],"book_id":"1431645","id":11500190,"rating":4,"book_title":"Liar's Poker","url":"https://book.douban.com/subject/1431645/"},{"status":"read","updated":"2007-02-28 01:34:08","user_id":"1000001","tags":["商业"],"book_id":"1421436","id":11128613,"rating":4,"book_title":"iCon Steve Jobs","url":"https://book.douban.com/subject/1421436/"},{"status":"read","updated":"2007-02-28 01:33:03","user_id":"1000001","tags":["小说"],"book_id":"1703544","id":11128591,"rating":3,"book_title":"兄弟（下）","url":"https://book.douban.com/subject/1703544/"},{"status":"read","updated":"2007-02-28 01:32:12","user_id":"1000001","tags":["小说"],"book_id":"2000552","id":11128569,"rating":4,"book_title":"State of Fear","url":"https://book.douban.com/subject/2000552/"},{"status":"read","updated":"2007-01-27 16:35:57","user_id":"1000001","tags":["商业","技术"],"book_id":"1427609","id":609307,"rating":4,"book_title":"The Search","url":"https://book.douban.com/subject/1427609/"},{"status":"read","updated":"2006-12-28 22:46:15","user_id":"1000001","tags":["fiction"],"book_id":"1418853","id":8555866,"rating":3,"book_title":"The Historian","url":"https://book.douban.com/subject/1418853/"},{"status":"read","updated":"2006-12-08 12:07:13","user_id":"1000001","book_id":"1355595","id":44295,"rating":4,"book_title":"Linked","url":"https://book.douban.com/subject/1355595/"},{"status":"read","updated":"2006-11-16 16:38:16","user_id":"1000001","book_id":"1919072","id":7198373,"rating":4,"book_title":"长尾理论","url":"https://book.douban.com/subject/1919072/"},{"status":"read","updated":"2006-10-31 13:47:20","user_id":"1000001","book_id":"1440300","id":6730970,"rating":3,"book_title":"The Google Story","url":"https://book.douban.com/subject/1440300/"},{"status":"read","updated":"2006-08-27 14:33:09","user_id":"1000001","tags":["金融","华尔街"],"book_id":"1798516","id":5129973,"rating":4,"book_title":"F.I.A.S.C.O.","url":"https://book.douban.com/subject/1798516/"},{"status":"read","updated":"2006-05-24 00:01:23","user_id":"1000001","tags":["文化","中国"],"book_id":"1777823","id":3198963,"rating":0,"book_title":"八十年代访谈录","url":"https://book.douban.com/subject/1777823/"},{"status":"read","updated":"2006-04-22 13:15:14","user_id":"1000001","book_id":"1351071","id":2573218,"rating":3,"book_title":"The World Is Flat","url":"https://book.douban.com/subject/1351071/"},{"status":"read","updated":"2006-04-22 13:13:33","user_id":"1000001","tags":["生态"],"book_id":"1471288","id":2573192,"rating":5,"book_title":"Collapse","url":"https://book.douban.com/subject/1471288/"},{"status":"read","updated":"2006-04-16 18:19:52","user_id":"1000001","book_id":"1292336","id":2464481,"rating":4,"book_title":"Freakonomics","url":"https://book.douban.com/subject/1292336/"},{"status":"read","updated":"2006-04-16 18:17:10","user_id":"1000001","tags":["商业","自传"],"book_id":"1527795","id":2464438,"rating":4,"book_title":"Pour Your Heart Into It","url":"https://book.douban.com/subject/1527795/"},{"status":"read","updated":"2006-04-16 18:15:12","user_id":"1000001","tags":["商业"],"book_id":"1431652","id":2464405,"rating":5,"book_title":"Built to Last","url":"https://book.douban.com/subject/1431652/"},{"status":"read","updated":"2006-04-05 20:00:26","user_id":"1000001","book_id":"1441244","id":737249,"rating":4,"book_title":"Barbarians at the Gate","url":"https://book.douban.com/subject/1441244/"},{"status":"read","updated":"2005-12-24 09:43:21","user_id":"1000001","tags":["物理","教材"],"book_id":"1451457","id":885810,"rating":0,"book_title":"A Modern Course in Statistical Physics","url":"https://book.douban.com/subject/1451457/"},{"status":"read","updated":"2005-12-02 11:08:06","user_id":"1000001","tags":["金融","传记","华尔街"],"book_id":"1440556","id":705065,"rating":4,"book_title":"Tearing Down the Walls","url":"https://book.douban.com/subject/1440556/"},{"status":"read","updated":"2005-12-02 11:05:52","user_id":"1000001","tags":["金融"],"book_id":"1440555","id":705058,"rating":4,"book_title":"A Random Walk Down Wall Street","url":"https://book.douban.com/subject/1440555/"},{"status":"read","updated":"2005-12-02 11:02:49","user_id":"1000001","tags":["小说","知识分子"],"book_id":"1424307","id":705042,"rating":4,"book_title":"The Unbearable Lightness of Being","url":"https://book.douban.com/subject/1424307/"},{"status":"read","updated":"2005-12-02 10:59:36","user_id":"1000001","tags":["科幻"],"book_id":"1440554","id":705036,"rating":0,"book_title":"The Man in the High Castle","url":"https://book.douban.com/subject/1440554/"},{"status":"read","updated":"2005-12-02 10:57:37","user_id":"1000001","tags":["传记","管理"],"book_id":"1431641","id":705029,"rating":4,"book_title":"The Second Coming of Steve Jobs","url":"https://book.douban.com/subject/1431641/"},{"status":"read","updated":"2005-12-02 01:39:00","user_id":"1000001","tags":["禅宗"],"book_id":"1417907","id":703846,"rating":4,"book_title":"Zen and the Art of Motorcycle Maintenance","url":"https://book.douban.com/subject/1417907/"},{"status":"read","updated":"2005-11-24 01:40:46","user_id":"1000001","book_id":"1376056","id":649042,"rating":5,"book_title":"The Name of the Rose","url":"https://book.douban.com/subject/1376056/"},{"status":"read","updated":"2005-11-17 13:31:31","user_id":"1000001","book_id":"1438789","id":608882,"rating":5,"book_title":"The Interpretation of Cultures","url":"https://book.douban.com/subject/1438789/"},{"status":"read","updated":"2005-11-13 20:34:23","user_id":"1000001","tags":["魔幻","小说"],"book_id":"1288972","id":399349,"rating":4,"book_title":"Harry Potter and the Half-Blood Prince","url":"https://book.douban.com/subject/1288972/"},{"status":"read","updated":"2005-08-24 18:08:01","user_id":"1000001","book_id":"1343525","id":191025,"rating":0,"book_title":"Harry Potter and the Order of the Phoenix","url":"https://book.douban.com/subject/1343525/"},{"status":"read","updated":"2005-08-07 00:11:08","user_id":"1000001","tags":["生存","小说"],"book_id":"1350063","id":85136,"rating":4,"book_title":"Life of Pi","url":"https://book.douban.com/subject/1350063/"},{"status":"read","updated":"2005-08-03 12:14:38","user_id":"1000001","tags":["金融","华尔街"],"book_id":"1401976","id":116215,"rating":4,"book_title":"When Genius Failed","url":"https://book.douban.com/subject/1401976/"},{"status":"read","updated":"2005-07-29 15:52:52","user_id":"1000001","book_id":"1341387","id":103078,"rating":2,"book_title":"Timeline","url":"https://book.douban.com/subject/1341387/"},{"status":"read","updated":"2005-07-27 23:07:09","user_id":"1000001","book_id":"1345685","id":30965,"rating":2,"book_title":"Einstein's Dreams","url":"https://book.douban.com/subject/1345685/"},{"status":"read","updated":"2005-07-20 23:46:23","user_id":"1000001","tags":["悬疑","畅销"],"book_id":"1343950","id":81664,"rating":4,"book_title":"The Da Vinci Code","url":"https://book.douban.com/subject/1343950/"},{"status":"read","updated":"2005-07-17 10:40:08","user_id":"1000001","tags":["时间旅行","小说"],"book_id":"1388182","id":44152,"rating":4,"book_title":"The Time Traveler's Wife","url":"https://book.douban.com/subject/1388182/"},{"status":"read","updated":"2005-07-06 22:03:03","user_id":"1000001","tags":["文革","回忆录"],"book_id":"1062423","id":41701,"rating":4,"book_title":"牛棚杂忆","url":"https://book.douban.com/subject/1062423/"},{"status":"read","updated":"2005-06-29 15:31:50","user_id":"1000001","tags":["京剧"],"book_id":"1067974","id":26897,"rating":4,"book_title":"彩色的花雨","url":"https://book.douban.com/subject/1067974/"},{"status":"read","updated":"2005-06-24 03:42:35","user_id":"1000001","tags":["传记","管理"],"book_id":"1049071","id":13331,"rating":3,"book_title":"杰克·韦尔奇自传","url":"https://book.douban.com/subject/1049071/"},{"status":"read","updated":"2005-06-12 02:22:25","user_id":"1000001","tags":["物理学家","传记"],"book_id":"1053174","id":6981,"rating":4,"book_title":"你干吗在乎别人怎么想？","url":"https://book.douban.com/subject/1053174/"},{"status":"read","updated":"2005-06-12 02:22:24","user_id":"1000001","tags":["魔幻","畅销"],"book_id":"1291202","id":6928,"rating":4,"book_title":"Harry Potter and the Goblet of Fire","url":"https://book.douban.com/subject/1291202/"},{"status":"read","updated":"2005-06-12 02:22:07","user_id":"1000001","tags":["cult","可笑","科幻","英国"],"book_id":"1291993","id":3920,"rating":4,"book_title":"The Hitchhiker's Guide to the Galaxy","url":"https://book.douban.com/subject/1291993/"},{"status":"read","updated":"2005-06-12 02:22:07","user_id":"1000001","tags":["PKD","科幻","电影原著"],"book_id":"1291996","id":3938,"rating":4,"book_title":"Do Androids Dream of Electric Sheep?","url":"https://book.douban.com/subject/1291996/"},{"status":"read","updated":"2005-06-12 02:22:07","user_id":"1000001","tags":["电影原著","科幻","经典"],"book_id":"1291997","id":3939,"rating":4,"book_title":"Dune","url":"https://book.douban.com/subject/1291997/"},{"status":"read","updated":"2005-06-12 02:22:07","user_id":"1000001","tags":["创新","创业","管理"],"book_id":"1291998","id":3946,"rating":4,"book_title":"Innovation and Entrepreneurship","url":"https://book.douban.com/subject/1291998/"},{"status":"read","updated":"2005-06-12 02:21:36","user_id":"1000001","tags":["金融","华尔街","经济史"],"book_id":"1227019","id":91,"rating":5,"book_title":"伟大的博弈","url":"https://book.douban.com/subject/1227019/"},{"status":"read","updated":"2005-06-12 02:21:36","user_id":"1000001","tags":["社会软件","传播","流行"],"book_id":"1291075","id":2883,"rating":4,"book_title":"The Tipping Point","url":"https://book.douban.com/subject/1291075/"},{"status":"read","updated":"2005-06-12 02:21:36","user_id":"1000001","tags":["非洲","自传","成长","最爱"],"book_id":"1291076","id":2884,"rating":5,"book_title":"West with the Night","url":"https://book.douban.com/subject/1291076/"},{"status":"read","updated":"2005-06-12 02:21:36","user_id":"1000001","tags":["无神论","科普","进化论","evolution"],"book_id":"1291215","id":2990,"rating":4,"book_title":"The Blind Watchmaker","url":"https://book.douban.com/subject/1291215/"},{"status":"read","updated":"2005-06-12 02:21:36","user_id":"1000001","tags":["美国","重新开始","普利策","电影原著","小说"],"book_id":"1291532","id":3305,"rating":4,"book_title":"The Shipping News","url":"https://book.douban.com/subject/1291532/"},{"status":"read","updated":"2005-06-12 02:21:35","user_id":"1000001","tags":["小说","最爱","中国文学"],"book_id":"1023658","id":1,"rating":5,"book_title":"许三观卖血记","url":"https://book.douban.com/subject/1023658/"},{"status":"read","updated":"2005-06-12 02:21:35","user_id":"1000001","tags":["物理学家","传记"],"book_id":"1037602","id":361,"rating":4,"book_title":"别闹了，费曼先生","url":"https://book.douban.com/subject/1037602/"},{"status":"read","updated":"2005-06-12 02:21:35","user_id":"1000001","tags":["中国历史","明清","历史"],"book_id":"1041482","id":92,"rating":5,"book_title":"万历十五年","url":"https://book.douban.com/subject/1041482/"},{"status":"read","updated":"2005-06-12 02:21:35","user_id":"1000001","tags":["非主流","自助旅行","旅游"],"book_id":"1054066","id":277,"rating":3,"book_title":"侠游中国","url":"https://book.douban.com/subject/1054066/"},{"status":"read","updated":"2005-06-12 02:21:35","user_id":"1000001","tags":["怀旧","北京","摄影","胡同"],"book_id":"1070203","id":64,"rating":4,"book_title":"京城胡同留真","url":"https://book.douban.com/subject/1070203/"},{"status":"read","updated":"2005-06-12 02:21:35","user_id":"1000001","tags":["文革","杨绛","知识分子","中国文学"],"book_id":"1078250","id":262,"rating":5,"book_title":"洗澡","url":"https://book.douban.com/subject/1078250/"},{"status":"read","updated":"2005-06-12 02:21:35","user_id":"1000001","tags":["汉字","语言","甲古文"],"book_id":"1078684","id":35,"rating":4,"book_title":"汉字密码（上下）","url":"https://book.douban.com/subject/1078684/"},{"status":"read","updated":"2005-06-12 02:21:35","user_id":"1000001","tags":["余华","成长","中国文学"],"book_id":"1082138","id":3187,"rating":5,"book_title":"在细雨中呼喊","url":"https://book.douban.com/subject/1082138/"},{"status":"read","updated":"2005-06-12 02:21:35","user_id":"1000001","tags":["自助旅行","山西","地理","旅游"],"book_id":"1083828","id":52,"rating":4,"book_title":"山西","url":"https://book.douban.com/subject/1083828/"},{"status":"read","updated":"2005-06-12 02:21:35","user_id":"1000001","tags":["设计模式","编程","经典"],"book_id":"1099305","id":164,"rating":4,"book_title":"设计模式","url":"https://book.douban.com/subject/1099305/"},{"status":"read","updated":"2005-06-12 02:21:35","user_id":"1000001","tags":["设计","界面","可用性","GUI"],"book_id":"1101529","id":2380,"rating":3,"book_title":"人本界面","url":"https://book.douban.com/subject/1101529/"},{"status":"read","updated":"2005-06-12 02:21:35","user_id":"1000001","tags":["影印","敏捷开发","编程"],"book_id":"1106301","id":2,"rating":4,"book_title":"敏捷软件开发（影印版）","url":"https://book.douban.com/subject/1106301/"},{"status":"read","updated":"2005-06-12 02:21:35","user_id":"1000001","tags":["中国文学"],"book_id":"1119829","id":1557,"rating":5,"book_title":"汪曾祺小说","url":"https://book.douban.com/subject/1119829/"},{"status":"read","updated":"2005-05-22 19:05:11","user_id":"1000001","tags":["中国历史","历史"],"book_id":"1015699","id":6926,"rating":4,"book_title":"中国大历史","url":"https://book.douban.com/subject/1015699/"},{"status":"read","updated":"2005-05-09 19:15:37","user_id":"1000001","tags":["欧洲漫画"],"book_id":"1033744","id":4428,"rating":5,"book_title":"丁丁在刚果","url":"https://book.douban.com/subject/1033744/"},{"status":"read","updated":"2005-04-01 22:40:29","user_id":"1000001","tags":["伪书","假"],"book_id":"1002197","id":254,"rating":1,"book_title":"执行力","url":"https://book.douban.com/subject/1002197/"},{"status":"read","updated":"2005-03-25 19:32:53","user_id":"1000001","tags":["自恋","经典"],"book_id":"1027334","id":152,"rating":5,"book_title":"多里安・格雷的画像","url":"https://book.douban.com/subject/1027334/"},{"status":"read","updated":"2005-03-10 02:22:37","user_id":"1000001","tags":["必读","编程","算法","经典"],"book_id":"1130500","id":53,"rating":5,"book_title":"计算机程序设计艺术（第1卷）","url":"https://book.douban.com/subject/1130500/"},{"status":"read","updated":"2005-03-10 02:16:51","user_id":"1000001","tags":["小说","中国文学"],"book_id":"1020961","id":51,"rating":5,"book_title":"棋王","url":"https://book.douban.com/subject/1020961/"}]